MANIFEST.in
Makefile
requirements.txt
setup.py
veb
vvv/__init__.py
vvv/api/__init__.py
vvv/api/app.py
vvv/api/aug.py
vvv/api/check.py
vvv/api/command.py
vvv/api/config.py
vvv/api/configurable.py
vvv/api/plugin.py
vvv/api/restartable.py
vvv/api/template.py
vvv/api/util.py
vvv/plugins/__init__.py
vvv/plugins/core/__init__.py
vvv/plugins/core/commands.py
vvv/plugins/core/plugin.py
vvv/plugins/help/__init__.py
vvv/plugins/help/commands.py
vvv/plugins/help/plugin.py
vvv/plugins/nginx/__init__.py
vvv/plugins/nginx/commands.py
vvv/plugins/nginx/plugin.py
vvv/plugins/nginx/server.py
vvv/plugins/nginx/templates.py
vvv/plugins/nodejs/__init__.py
vvv/plugins/nodejs/nodejs.py
vvv/plugins/nodejs/plugin.py
vvv/plugins/phpfpm/__init__.py
vvv/plugins/phpfpm/phpfpm.py
vvv/plugins/phpfpm/plugin.py
vvv/plugins/phpfpm/templates.py
vvv/plugins/plugins/__init__.py
vvv/plugins/plugins/commands.py
vvv/plugins/plugins/plugin.py
vvv/plugins/python/__init__.py
vvv/plugins/python/plugin.py
vvv/plugins/python/python.py
vvv/plugins/supervisor/__init__.py
vvv/plugins/supervisor/plugin.py
vvv/plugins/supervisor/supervisor.aug
vvv/plugins/supervisor/supervisor.py
vvveb.egg-info/PKG-INFO
vvveb.egg-info/SOURCES.txt
vvveb.egg-info/dependency_links.txt
vvveb.egg-info/requires.txt
vvveb.egg-info/top_level.txt