Metadata-Version: 1.0
Name: vvveb
Version: 1.0.29
Summary: An automatic website hosting configurator
Home-page: https://github.com/ajenti/veb
Author: Eugene Pankov
Author-email: e@ajenti.org
License: UNKNOWN
Platform: UNKNOWN
